lindr/__init__.py
lindr/_base.py
lindr/_exceptions.py
lindr/_version.py
lindr/client.py
lindr/resources/__init__.py
lindr/resources/checkpoints.py
lindr/resources/comparisons.py
lindr/resources/datasets.py
lindr/resources/evals.py
lindr/resources/personas.py
lindr/resources/training_data.py
lindr/types/__init__.py
lindr/types/checkpoints.py
lindr/types/common.py
lindr/types/comparisons.py
lindr/types/datasets.py
lindr/types/evals.py
lindr/types/personas.py
lindr-0.5.0.dist-info/METADATA
lindr-0.5.0.dist-info/WHEEL
lindr-0.5.0.dist-info/RECORD
